base_version_checker-0.3.0.dist-info/licenses/LICENSE
version_checker/Readme.md
version_checker/__init__.py
version_checker/bumpversion_cfg_example.txt
version_checker/cli.py
version_checker/constants.py
version_checker/utils.py
base_version_checker-0.3.0.dist-info/METADATA
base_version_checker-0.3.0.dist-info/WHEEL
base_version_checker-0.3.0.dist-info/entry_points.txt
base_version_checker-0.3.0.dist-info/top_level.txt
base_version_checker-0.3.0.dist-info/RECORD
