Metadata-Version: 2.4
Name: base-version-checker
Version: 0.3.0
Summary: Dev utility to verify hardcoded versions are in sync & updated
Home-page: https://github.com/kmfarley11/version-checker
Author: kmfarley11
Author-email: kmfarley11@gmail.com
Classifier: Programming Language :: Python :: 3
Classifier: License :: OSI Approved :: MIT License
Classifier: Operating System :: OS Independent
Requires-Python: >=3.6
License-File: LICENSE
Requires-Dist: GitPython
Requires-Dist: bump2version
Requires-Dist: semver
Provides-Extra: build
Requires-Dist: build[virtualenv]; extra == "build"
Requires-Dist: setuptools; extra == "build"
Requires-Dist: twine; extra == "build"
Provides-Extra: test
Requires-Dist: pytest; extra == "test"
Requires-Dist: pytest-mock; extra == "test"
Requires-Dist: pytest-cov; extra == "test"
Requires-Dist: coverage; extra == "test"
Requires-Dist: mock; extra == "test"
Provides-Extra: dev
Requires-Dist: build[virtualenv]; extra == "dev"
Requires-Dist: setuptools; extra == "dev"
Requires-Dist: twine; extra == "dev"
Requires-Dist: pytest; extra == "dev"
Requires-Dist: pytest-mock; extra == "dev"
Requires-Dist: pytest-cov; extra == "dev"
Requires-Dist: coverage; extra == "dev"
Requires-Dist: mock; extra == "dev"
Requires-Dist: pylint; extra == "dev"
Dynamic: license-file
